aicscytoparam-0.2.1.dist-info/METADATA
aicscytoparam-0.2.1.dist-info/WHEEL
aicscytoparam-0.2.1.dist-info/entry_points.txt
aicscytoparam-0.2.1.dist-info/licenses/LICENSE
aicscytoparam-0.2.1.dist-info/licenses/LICENSE.txt
aicscytoparam/__init__.py
aicscytoparam/alignment/__init__.py
aicscytoparam/alignment/generic_2d_shape.py
aicscytoparam/alignment/shape_library_2d.py
aicscytoparam/bin/__init__.py
aicscytoparam/bin/my_example.py
aicscytoparam/cytoparam.py
aicscytoparam/tests/__init__.py
aicscytoparam/tests/dummy_test.py
aicscytoparam/utils.py
aicscytoparam-0.2.1.dist-info/RECORD
