Metadata-Version: 2.1
Name: aicscytoparam
Version: 0.2.1
Summary: Cytoplasm parameterization using spherical harmonics
Keywords: aicscytoparam
Author-Email: Matheus Viana <matheus.viana@alleninstitute.org>
License: Allen Institute Software License
Classifier: Development Status :: 5 - Production/Stable
Classifier: Intended Audience :: Science/Research
Classifier: License :: Free for non-commercial use
Classifier: Natural Language :: English
Classifier: Programming Language :: Python :: 3 :: Only
Project-URL: Homepage, https://github.com/AllenCell/aics-cytoparam
Requires-Python: >=3.9
Requires-Dist: setuptools
Requires-Dist: aicsimageio
Requires-Dist: aicsshparam
Requires-Dist: pyshtools>=4.13.1
Provides-Extra: setup
Requires-Dist: pytest-runner; extra == "setup"
Requires-Dist: wheel; extra == "setup"
Provides-Extra: test
Requires-Dist: black; extra == "test"
Requires-Dist: flake8; extra == "test"
Requires-Dist: Flake8-pyproject; extra == "test"
Requires-Dist: flake8-debugger; extra == "test"
Requires-Dist: pytest; extra == "test"
Requires-Dist: pytest-cov; extra == "test"
Requires-Dist: pytest-raises; extra == "test"
Provides-Extra: dev
Requires-Dist: Sphinx; extra == "dev"
Requires-Dist: black; extra == "dev"
Requires-Dist: bump-my-version; extra == "dev"
Requires-Dist: coverage; extra == "dev"
Requires-Dist: flake8; extra == "dev"
Requires-Dist: Flake8-pyproject; extra == "dev"
Requires-Dist: flake8-debugger; extra == "dev"
Requires-Dist: ipython; extra == "dev"
Requires-Dist: myst-parser; extra == "dev"
Requires-Dist: pytest; extra == "dev"
Requires-Dist: pytest-cov; extra == "dev"
Requires-Dist: pytest-raises; extra == "dev"
Requires-Dist: pytest-runner; extra == "dev"
Requires-Dist: pytest-runner; extra == "dev"
Requires-Dist: sphinx_rtd_theme; extra == "dev"
Requires-Dist: tox; extra == "dev"
Requires-Dist: twine; extra == "dev"
Requires-Dist: wheel; extra == "dev"
Requires-Dist: wheel; extra == "dev"
Provides-Extra: all
Requires-Dist: Sphinx; extra == "all"
Requires-Dist: aicsimageio; extra == "all"
Requires-Dist: aicsshparam; extra == "all"
Requires-Dist: black; extra == "all"
Requires-Dist: bump-my-version; extra == "all"
Requires-Dist: coverage; extra == "all"
Requires-Dist: flake8; extra == "all"
Requires-Dist: Flake8-pyproject; extra == "all"
Requires-Dist: flake8-debugger; extra == "all"
Requires-Dist: ipython; extra == "all"
Requires-Dist: myst-parser; extra == "all"
Requires-Dist: pytest; extra == "all"
Requires-Dist: pytest-cov; extra == "all"
Requires-Dist: pytest-raises; extra == "all"
Requires-Dist: pytest-runner; extra == "all"
Requires-Dist: pytest-runner; extra == "all"
Requires-Dist: sphinx_rtd_theme; extra == "all"
Requires-Dist: tox; extra == "all"
Requires-Dist: twine; extra == "all"
Requires-Dist: wheel; extra == "all"
Requires-Dist: wheel; extra == "all"
